__init__.py
main.py
js_python_starter-2.5.2.dist-info/licenses/LICENSE
util/__init__.py
util/healthcheck.py
util/logging.py
js_python_starter-2.5.2.dist-info/METADATA
js_python_starter-2.5.2.dist-info/WHEEL
js_python_starter-2.5.2.dist-info/top_level.txt
js_python_starter-2.5.2.dist-info/RECORD
