Metadata-Version: 2.4
Name: js-python-starter
Version: 2.5.2
Summary: A starter project for quickly setting up new Python apps
Author-email: jnstockley <jnstockley@users.noreply.github.com>
Project-URL: Homepage, https://github.com/jnstockley/python-starter
Project-URL: Repository, https://github.com/jnstockley/python-starter.git
Project-URL: Issues, https://github.com/jnstockley/python-starter/issues
Keywords: starter,template,python
Classifier: Programming Language :: Python :: 3
Requires-Python: <4.0,>=3.13
License-File: LICENSE
Requires-Dist: python-dotenv==1.2.1
Dynamic: license-file
